README.txt
lib_logger.py
setup.py
lib_logger.egg-info/PKG-INFO
lib_logger.egg-info/SOURCES.txt
lib_logger.egg-info/dependency_links.txt
lib_logger.egg-info/top_level.txt