Metadata-Version: 1.0
Name: lib-logger
Version: 1.2
Summary: Add-on to the logging package
Home-page: UNKNOWN
Author: Albert Benzimra
Author-email: benzimra@comcast.net
License: UNKNOWN
Platform: UNKNOWN
